assemblyline_v4_service/VERSION
assemblyline_v4_service/__init__.py
assemblyline_v4_service/healthz.py
assemblyline_v4_service/py.typed
assemblyline_v4_service/run_service.py
assemblyline_v4_service/common/__init__.py
assemblyline_v4_service/common/api.py
assemblyline_v4_service/common/base.py
assemblyline_v4_service/common/helper.py
assemblyline_v4_service/common/ocr.py
assemblyline_v4_service/common/ontology_helper.py
assemblyline_v4_service/common/request.py
assemblyline_v4_service/common/result.py
assemblyline_v4_service/common/task.py
assemblyline_v4_service/common/utils.py
assemblyline_v4_service/dev/__init__.py
assemblyline_v4_service/dev/run_service_once.py
assemblyline_v4_service/dev/updater.py
assemblyline_v4_service/updater/__init__.py
assemblyline_v4_service/updater/__main__.py
assemblyline_v4_service/updater/app.py
assemblyline_v4_service/updater/client.py
assemblyline_v4_service/updater/gunicorn_config.py
assemblyline_v4_service/updater/helper.py
assemblyline_v4_service/updater/updater.py
assemblyline_v4_service-4.7.0.1.dist-info/licenses/LICENCE.md
test/__init__.py
test/conftest.py
test/test_healthz.py
test/test_run_privileged_service.py
test/test_run_service.py
test/test_common/__init__.py
test/test_common/test_api.py
test/test_common/test_base.py
test/test_common/test_helper.py
test/test_common/test_ocr.py
test/test_common/test_ontology_helper.py
test/test_common/test_request.py
test/test_common/test_result.py
test/test_common/test_task.py
test/test_common/test_utils.py
assemblyline_v4_service-4.7.0.1.dist-info/METADATA
assemblyline_v4_service-4.7.0.1.dist-info/WHEEL
assemblyline_v4_service-4.7.0.1.dist-info/top_level.txt
assemblyline_v4_service-4.7.0.1.dist-info/RECORD
