Metadata-Version: 2.4
Name: assemblyline-v4-service
Version: 4.7.0.1
Summary: Assemblyline 4 - Service base
Home-page: https://github.com/CybercentreCanada/assemblyline-v4-service/
Author: CCCS Assemblyline development team
Author-email: assemblyline@cyber.gc.ca
License: MIT
Keywords: assemblyline automated malware analysis gc canada cse-cst cse cst cyber cccs
Classifier: Development Status :: 5 - Production/Stable
Classifier: Intended Audience :: Developers
Classifier: Topic :: Software Development :: Libraries
Classifier: License :: OSI Approved :: MIT License
Classifier: Programming Language :: Python :: 3.7
Classifier: Programming Language :: Python :: 3.8
Classifier: Programming Language :: Python :: 3.9
Classifier: Programming Language :: Python :: 3.10
Classifier: Programming Language :: Python :: 3.11
Classifier: Programming Language :: Python :: 3.12
License-File: LICENCE.md
Requires-Dist: assemblyline
Requires-Dist: assemblyline-core
Requires-Dist: cart
Requires-Dist: fuzzywuzzy
Requires-Dist: pefile
Requires-Dist: pillow!=10.1.0,!=10.2.0
Requires-Dist: python-Levenshtein
Requires-Dist: regex
Provides-Extra: updater
Requires-Dist: gunicorn[gevent]; extra == "updater"
Requires-Dist: flask; extra == "updater"
Requires-Dist: gitpython; extra == "updater"
Requires-Dist: git-remote-codecommit; extra == "updater"
Requires-Dist: psutil; extra == "updater"
Dynamic: author
Dynamic: author-email
Dynamic: classifier
Dynamic: description
Dynamic: description-content-type
Dynamic: home-page
Dynamic: keywords
Dynamic: license
Dynamic: license-file
Dynamic: provides-extra
Dynamic: requires-dist
Dynamic: summary
